namekox_core/__init__.py
namekox_core/constants.py
namekox_core/exceptions.py
namekox_core/cli/__init__.py
namekox_core/cli/main.py
namekox_core/cli/subcmd/__init__.py
namekox_core/cli/subcmd/base.py
namekox_core/cli/subcmd/config.py
namekox_core/cli/subcmd/create.py
namekox_core/cli/subcmd/run.py
namekox_core/cli/subcmd/shell.py
namekox_core/core/__init__.py
namekox_core/core/friendly.py
namekox_core/core/generator.py
namekox_core/core/loaders.py
namekox_core/core/spawning.py
namekox_core/core/timezone.py
namekox_core/core/parsers/__init__.py
namekox_core/core/parsers/base.py
namekox_core/core/parsers/patterns.py
namekox_core/core/service/__init__.py
namekox_core/core/service/container.py
namekox_core/core/service/context.py
namekox_core/core/service/dependency.py
namekox_core/core/service/discovery.py
namekox_core/core/service/entrypoint.py
namekox_core/core/service/extension.py
namekox_core/core/service/runner.py
namekox_core-0.0.25.dist-info/METADATA
namekox_core-0.0.25.dist-info/WHEEL
namekox_core-0.0.25.dist-info/entry_points.txt
namekox_core-0.0.25.dist-info/top_level.txt
namekox_core-0.0.25.dist-info/zip-safe
namekox_core-0.0.25.dist-info/RECORD
