Metadata-Version: 2.1
Name: namekox-core
Version: 0.0.25
Summary: namekox core
Home-page: https://forcemain.github.io/
Author: forcemain
License: Apache License, Version 2.0
Platform: UNKNOWN
Classifier: Programming Language :: Python
Classifier: Operating System :: MacOS :: MacOS X
Classifier: Operating System :: POSIX
Classifier: Programming Language :: Python :: 2
Classifier: Programming Language :: Python :: 2.7
Classifier: Programming Language :: Python :: 3
Classifier: Programming Language :: Python :: 3.5
Classifier: Programming Language :: Python :: 3.6
Classifier: Topic :: Internet
Classifier: Topic :: Software Development :: Libraries :: Python Modules
Classifier: Intended Audience :: Developers
Requires-Dist: eventlet (==0.27.0)
Requires-Dist: gitpython (==2.1.15)
Requires-Dist: PyYAML (==5.3.1)
Requires-Dist: six (==1.15.0)
Requires-Dist: pytz (==2018.5)
